{
  "include": [
    "about"
  ], 
  "blogtitle": "Draconion", 
  "url": "blag.fallingduck.net", 
  "tagline": "My awesome blog!", 
  "archiveuri": "index.html", 
  "posts": [
    {
      "date": "December 5, 2014", 
      "tagline": "In which I create my new blog.", 
      "link": "first-post", 
      "title": "First Post"
    }
  ], 
  "uri": "{0}.html", 
  "sidebar": [
    [
      "ARCHIVE", 
      "."
    ], 
    [
      "ABOUT", 
      "about.html"
    ], 
    [
      "SUBSCRIBE", 
      "feed.xml"
    ]
  ]
}
